gradio_mindbox/__init__.py
gradio_mindbox/mindbox.py
gradio_mindbox/mindbox.pyi
gradio_mindbox/templates/component/index.js
gradio_mindbox/templates/component/style.css
gradio_mindbox/templates/example/index.js
gradio_mindbox/templates/example/style.css
gradio_mindbox-0.0.2.dist-info/METADATA
gradio_mindbox-0.0.2.dist-info/WHEEL
gradio_mindbox-0.0.2.dist-info/RECORD
